adaptive_timer/__init__.py
adaptive_timer/interval.py
adaptive_timer/timer.py
adaptive_timer-0.3.13.dist-info/METADATA
adaptive_timer-0.3.13.dist-info/WHEEL
adaptive_timer-0.3.13.dist-info/licenses/LICENSE
adaptive_timer-0.3.13.dist-info/RECORD
