Metadata-Version: 2.4
Name: adaptive-timer
Version: 0.3.13
Summary: Executes a workload at a designated interval while minimizing time variance
Project-URL: Repository, https://github.com/bvett/adaptive-timer.git
Project-URL: Issues, https://github.com/bvett/adaptive-timer/issues
Author-email: Brian Vetter <bvetter@gmail.com>
License-Expression: MIT
License-File: LICENSE
Classifier: Development Status :: 3 - Alpha
Classifier: Operating System :: OS Independent
Classifier: Programming Language :: Python :: 3
Classifier: Programming Language :: Python :: Implementation :: MicroPython
Requires-Python: >=3.9
Requires-Dist: pycopy-cpython-utime>=0.5.2
